vulture/libs/fetch_functions/__init__.py
vulture/libs/fetch_functions/fetchData.py
vultureClient-0.0.3.dist-info/METADATA
vultureClient-0.0.3.dist-info/WHEEL
vultureClient-0.0.3.dist-info/top_level.txt
vultureClient-0.0.3.dist-info/zip-safe
vultureClient-0.0.3.dist-info/RECORD
