Metadata-Version: 2.1
Name: vultureClient
Version: 0.0.3
Summary: vulture-client: To fetch data from Vulture
Home-page: UNKNOWN
Author: UNKNOWN
Author-email: UNKNOWN
License: UNKNOWN
Platform: UNKNOWN
Requires-Dist: pandas (>=1.0.3)
